FlashGBX/DataTransfer.py
FlashGBX/FlashGBX.py
FlashGBX/FlashGBX_CLI.py
FlashGBX/FlashGBX_GUI.py
FlashGBX/Flashcart.py
FlashGBX/GBMemory.py
FlashGBX/LK_Device.py
FlashGBX/Mapper.py
FlashGBX/PocketCamera.py
FlashGBX/PocketCameraWindow.py
FlashGBX/RomFileAGB.py
FlashGBX/RomFileDMG.py
FlashGBX/UserInputDialog.py
FlashGBX/Util.py
FlashGBX/__init__.py
FlashGBX/__main__.py
FlashGBX/fw_GBFlash.py
FlashGBX/fw_GBxCartRW_v1_3.py
FlashGBX/fw_GBxCartRW_v1_4.py
FlashGBX/fw_JoeyJr.py
FlashGBX/hw_GBFlash.py
FlashGBX/hw_GBxCartRW.py
FlashGBX/hw_JoeyJr.py
FlashGBX/pyside.py
FlashGBX/res/Third Party Notices.md
FlashGBX/res/config.zip
FlashGBX/res/fw_GBFlash.zip
FlashGBX/res/fw_GBxCart_RW_Mini_v1_0.zip
FlashGBX/res/fw_GBxCart_RW_XMAS_v1_0.zip
FlashGBX/res/fw_GBxCart_RW_v1_1_v1_2.zip
FlashGBX/res/fw_GBxCart_RW_v1_3.zip
FlashGBX/res/fw_GBxCart_RW_v1_4.zip
FlashGBX/res/fw_GBxCart_RW_v1_4a.zip
FlashGBX/res/fw_JoeyJr.zip
FlashGBX/res/icon.ico
FlashGBX/res/icon.png
FlashGBX/res/pc_frame.png
FlashGBX-4.4.dist-info/LICENSE
FlashGBX-4.4.dist-info/METADATA
FlashGBX-4.4.dist-info/WHEEL
FlashGBX-4.4.dist-info/entry_points.txt
FlashGBX-4.4.dist-info/top_level.txt
FlashGBX-4.4.dist-info/RECORD
