Metadata-Version: 2.2
Name: FlashGBX
Version: 4.4
Summary: Reads and writes Game Boy and Game Boy Advance cartridge data
Home-page: https://github.com/lesserkuma/FlashGBX
Author: Lesserkuma
Project-URL: Source, https://github.com/lesserkuma/FlashGBX/
Project-URL: Tracker, https://github.com/lesserkuma/FlashGBX/issues
Classifier: Development Status :: 5 - Production/Stable
Classifier: Environment :: X11 Applications :: Qt
Classifier: Topic :: Terminals :: Serial
Classifier: Operating System :: OS Independent
Classifier: Programming Language :: Python :: 3
Classifier: License :: OSI Approved :: GNU General Public License v3 (GPLv3)
Classifier: Intended Audience :: End Users/Desktop
Classifier: Intended Audience :: Developers
Requires-Python: >=3.7
License-File: LICENSE
Requires-Dist: pyserial>=3.5
Requires-Dist: Pillow
Requires-Dist: setuptools
Requires-Dist: requests
Requires-Dist: python-dateutil
Provides-Extra: qt5
Requires-Dist: PySide2>=5.14; extra == "qt5"
Provides-Extra: qt6
Requires-Dist: PySide6; extra == "qt6"
Dynamic: author
Dynamic: classifier
Dynamic: description
Dynamic: description-content-type
Dynamic: home-page
Dynamic: project-url
Dynamic: provides-extra
Dynamic: requires-dist
Dynamic: requires-python
Dynamic: summary
